{
  "sections": {
    "main": {
      "type": "restaurant-about-page",
      "settings": {
        "hero_image": "shopify://shop_images/Screenshot_2026-05-16_135237.png",
        "hero_tag": "Est. 2012 · София",
        "hero_title_a": "За",
        "hero_title_em": "нас",
        "hero_subtitle": "Добре дошли в Суши Бар <em>Манго</em> — място, където свежестта и вкусът се срещат.",
        "hero_cta_label": "Разбери повече",
        "hero_cta_link": "#story",
        "side1_image": "shopify://shop_images/Screenshot_2026-05-16_135237.png",
        "side1_label": "Поръчай",
        "side1_link": "/pages/menu",
        "side2_image": "shopify://shop_images/Screenshot_2026-05-16_135237.png",
        "side2_label": "Свържи се с нас",
        "side2_link": "/pages/contact",
        "side3_image": "shopify://shop_images/Screenshot_2026-05-16_135237.png",
        "side3_label": "Галерия",
        "side3_link": "/pages/gallery",
        "marquee_word": "MANGO",
        "story_image": "shopify://shop_images/Screenshot_2026-05-16_135237.png",
        "story_caption": "шеф Танака",
        "story_kicker": "НАШАТА ИСТОРИЯ",
        "story_line_1": "Една кухня,",
        "story_line_2": "една",
        "story_line_2_em": "страст.",
        "dropcap": "М",
        "story_lead": "анго е родено от любовта към японската традиция и желанието да донесем истинското суши в България. От една малка кухня преди повече от десет години — до място, в което се срещат майсторски нож, прясна риба и съвременна атмосфера.",
        "story_body": "Всяко рулце е приготвено ръчно — с уважение към продукта и с прецизност, която сме научили от истинските майстори на занаята.",
        "stat_1_num": "10+",
        "stat_1_label": "години",
        "stat_2_num": "120",
        "stat_2_label": "ястия",
        "stat_3_num": "50k+",
        "stat_3_label": "клиенти",
        "collage_kicker": "МОМЕНТИ",
        "collage_line_1": "Прецизност",
        "collage_line_2": "хапка по хапка.",
        "collage_image_1": "shopify://shop_images/Screenshot_2026-05-16_135237.png",
        "collage_caption_1": "ножът",
        "collage_image_2": "shopify://shop_images/Screenshot_2026-05-16_135237.png",
        "collage_caption_2": "мигът",
        "collage_image_3": "shopify://shop_images/Screenshot_2026-05-16_135237.png",
        "collage_caption_3": "рибата",
        "collage_image_4": "shopify://shop_images/Screenshot_2026-05-16_135237.png",
        "collage_caption_4": "детайлът",
        "collage_image_5": "shopify://shop_images/Screenshot_2026-05-16_135237.png",
        "collage_caption_5": "ароматът",
        "video_poster": "shopify://shop_images/Screenshot_2026-05-16_135237.png",
        "video_kicker": "ВЛЕЗ В НАШИЯ СВЯТ",
        "video_line_1": "Кухнята е",
        "video_line_1_em": "сцена.",
        "video_line_2": "Готвачът е",
        "video_line_2_em": "артистът.",
        "video_caption": "поглед зад кулисите",
        "principles_kicker": "НАШИТЕ ПРИНЦИПИ",
        "principles_line_1": "Три неща,",
        "principles_line_2": "които ни",
        "principles_line_2_em": "водят.",
        "p1_title": "Свежи съставки",
        "p1_text": "Рибата идва ежедневно. Зеленчуците — от локални производители. Без компромиси.",
        "p2_title": "Майстори в занаята",
        "p2_text": "Готвачите ни се обучават години, за да достигнат прецизността на японското суши.",
        "p3_title": "Уют и гостоприемство",
        "p3_text": "От топлото посрещане до последната хапка — всеки детайл е обмислен.",
        "quote_image": "shopify://shop_images/Screenshot_2026-05-16_135237.png",
        "quote_text": "<p>Сушито не е просто храна — то е <em>разказ.</em> И всеки път, когато режа парче риба, мисля за човека, който ще го опита.</p>",
        "quote_name": "ШЕФ КОДЗИ ТАНАКА",
        "quote_role": "Главен суши майстор",
        "strip_image_1": "shopify://shop_images/Screenshot_2026-05-16_135237.png",
        "strip_image_2": "shopify://shop_images/Screenshot_2026-05-16_135237.png",
        "strip_image_3": "shopify://shop_images/Screenshot_2026-05-16_135237.png",
        "strip_image_4": "shopify://shop_images/Screenshot_2026-05-16_135237.png",
        "banner_image": "shopify://shop_images/Screenshot_2026-05-16_135237.png",
        "banner_line_1": "Създадено",
        "banner_line_1_em": "с любов.",
        "banner_line_2": "Подадено с",
        "banner_line_2_em": "уважение.",
        "banner_cta_primary": "ВИЖ МЕНЮТО",
        "banner_cta_secondary": "РЕЗЕРВИРАЙ МАСА",
        "menu_url": "/pages/menu",
        "contact_url": "/pages/contact"
      }
    }
  },
  "order": [
    "main"
  ]
}
